LICENSE.txt
MANIFEST.in
README.rst
setup.py
dfp/__init__.py
dfp/static/js/dfp.js
dfp/templatetags/__init__.py
dfp/templatetags/dfp.py
django_responsive_dfp.egg-info/PKG-INFO
django_responsive_dfp.egg-info/SOURCES.txt
django_responsive_dfp.egg-info/dependency_links.txt
django_responsive_dfp.egg-info/not-zip-safe
django_responsive_dfp.egg-info/requires.txt
django_responsive_dfp.egg-info/top_level.txt