Metadata-Version: 1.0
Name: django-responsive-dfp
Version: 0.1.2.3
Summary: Responsive ads using mediaquery for dfp.
Home-page: http://github.com/dcharbonnier/django-responsive-dfp
Author: David Charbonnier
Author-email: d.charbonnier@oxys.net
License: License :: OSI Approved :: MIT License
Keywords: django dfp ads responsive
Platform: UNKNOWN
Classifier: Development Status :: 4 - Beta
Classifier: Environment :: Web Environment
Classifier: Intended Audience :: Developers
Classifier: License :: OSI Approved :: BSD License
Classifier: Operating System :: OS Independent
Classifier: Programming Language :: Python
Classifier: Framework :: Django
